ceonmedia_s3/README.md
ceonmedia_s3/__init__.py
ceonmedia_s3/_s3_manager.py
ceonmedia_s3/_submission.py
ceonmedia_s3/assets.py
ceonmedia_s3/buckets.py
ceonmedia_s3/constants.py
ceonmedia_s3/errors.py
ceonmedia_s3/job.py
ceonmedia_s3/project.py
ceonmedia_s3/public.py
ceonmedia_s3/submission.py
ceonmedia_s3/core/__init__.py
ceonmedia_s3/core/base.py
ceonmedia_s3/core/copy.py
ceonmedia_s3/core/delete.py
ceonmedia_s3/core/download.py
ceonmedia_s3/core/inspect.py
ceonmedia_s3/core/json_s3.py
ceonmedia_s3/core/presigned.py
ceonmedia_s3/core/upload.py
ceonmedia_s3/log/__init__.py
ceonmedia_s3/log/_diagnostics.py
ceonmedia_s3/log/_formats.py
ceonmedia_s3/log/_formatters.py
ceonmedia_s3/log/_handlers.py
ceonmedia_s3/log/_log.py
ceonmedia_s3/log/_loggers.py
ceonmedia_s3/log/_logging_info.py
ceonmedia_s3/log/_logging_setup.py
ceonmedia_s3/log/pretty_printer.py
ceonmedia_s3-0.2.2.dist-info/METADATA
ceonmedia_s3-0.2.2.dist-info/WHEEL
ceonmedia_s3-0.2.2.dist-info/RECORD
