Metadata-Version: 2.4
Name: ceonmedia-s3
Version: 0.2.2
Summary: Developer interface for interacting with ceonmedia S3 storage
Author-email: Dayne Kolk <daynekolk@hotmail.com>
Requires-Python: >=3.11
